memota/__init__.py
memota/memota.py
memota/ram.py
memota-0.0.7.dist-info/LICENSE
memota-0.0.7.dist-info/METADATA
memota-0.0.7.dist-info/WHEEL
memota-0.0.7.dist-info/entry_points.txt
memota-0.0.7.dist-info/top_level.txt
memota-0.0.7.dist-info/RECORD
