Metadata-Version: 2.1
Name: memota
Version: 0.0.7
Summary: cli for ram monitoring
Author: Bovur
Keywords: python,ram,monitoring
Classifier: Development Status :: 1 - Planning
Classifier: Intended Audience :: Developers
Classifier: Programming Language :: Python :: 3
Classifier: Operating System :: Unix
Classifier: Operating System :: MacOS :: MacOS X
Classifier: Operating System :: Microsoft :: Windows
License-File: LICENSE
Requires-Dist: psutil (==5.9.4)
Requires-Dist: python-daemon (==2.3.2)
Requires-Dist: click (==8.1.3)
Requires-Dist: lockfile (==0.12.2)
